bable_interface/__init__.py
bable_interface/bable_interface.py
bable_interface/flatbuffers_functions.py
bable_interface/utils.py
bable_interface/BaBLE/BaBLEError.py
bable_interface/BaBLE/CancelConnection.py
bable_interface/BaBLE/Characteristic.py
bable_interface/BaBLE/Connect.py
bable_interface/BaBLE/Controller.py
bable_interface/BaBLE/ControllerAdded.py
bable_interface/BaBLE/ControllerRemoved.py
bable_interface/BaBLE/Device.py
bable_interface/BaBLE/DeviceConnected.py
bable_interface/BaBLE/DeviceDisconnected.py
bable_interface/BaBLE/DeviceFound.py
bable_interface/BaBLE/Disconnect.py
bable_interface/BaBLE/EmitNotification.py
bable_interface/BaBLE/Exit.py
bable_interface/BaBLE/GetConnectedDevices.py
bable_interface/BaBLE/GetControllerInfo.py
bable_interface/BaBLE/GetControllersIds.py
bable_interface/BaBLE/GetControllersList.py
bable_interface/BaBLE/Model.py
bable_interface/BaBLE/NotificationReceived.py
bable_interface/BaBLE/Packet.py
bable_interface/BaBLE/Payload.py
bable_interface/BaBLE/ProbeCharacteristics.py
bable_interface/BaBLE/ProbeServices.py
bable_interface/BaBLE/ReadCentral.py
bable_interface/BaBLE/ReadPeripheral.py
bable_interface/BaBLE/Ready.py
bable_interface/BaBLE/Service.py
bable_interface/BaBLE/SetAdvertising.py
bable_interface/BaBLE/SetConnectable.py
bable_interface/BaBLE/SetDiscoverable.py
bable_interface/BaBLE/SetGATTTable.py
bable_interface/BaBLE/SetPowered.py
bable_interface/BaBLE/StartScan.py
bable_interface/BaBLE/StatusCode.py
bable_interface/BaBLE/StopScan.py
bable_interface/BaBLE/WriteCentral.py
bable_interface/BaBLE/WritePeripheral.py
bable_interface/BaBLE/WriteWithoutResponseCentral.py
bable_interface/BaBLE/WriteWithoutResponsePeripheral.py
bable_interface/BaBLE/__init__.py
bable_interface/bin/.gitkeep
bable_interface/bin/bable-bridge-linux
bable_interface/commands/__init__.py
bable_interface/commands/commands_manager.py
bable_interface/commands/commands_py2.py
bable_interface/commands/commands_py3.py
bable_interface/models/__init__.py
bable_interface-1.2.1.dist-info/METADATA
bable_interface-1.2.1.dist-info/WHEEL
bable_interface-1.2.1.dist-info/entry_points.txt
bable_interface-1.2.1.dist-info/top_level.txt
bable_interface-1.2.1.dist-info/RECORD
