Metadata-Version: 2.1
Name: bable-interface
Version: 1.2.1
Summary: Python interface for BaBLE
Home-page: https://github.com/iotile/baBLE/interfaces/python
Author: Arch
Author-email: info@archsys.io
License: MIT
Keywords: bable,arch,bridge,BLE,Bluetooth,cross-platform
Platform: UNKNOWN
Classifier: Programming Language :: Python
Classifier: Programming Language :: Python :: 2
Classifier: Programming Language :: Python :: 2.7
Classifier: Programming Language :: Python :: 3
Classifier: Programming Language :: Python :: 3.6
Classifier: Development Status :: 3 - Alpha
Classifier: License :: OSI Approved :: MIT License
Classifier: Operating System :: OS Independent
